CELLULAR_CL/__init__.py
CELLULAR_CL/functions/__init__.py
CELLULAR_CL/functions/data_preprocessing.py
CELLULAR_CL/functions/make_cell_type_representations.py
CELLULAR_CL/functions/predict.py
CELLULAR_CL/functions/train.py
CELLULAR_CL/models/CELLULAR_model.py
CELLULAR_CL/models/ModelClassifier.py
CELLULAR_CL/models/__init__.py
CELLULAR_CL-0.0.4.dist-info/LICENSE.txt
CELLULAR_CL-0.0.4.dist-info/METADATA
CELLULAR_CL-0.0.4.dist-info/WHEEL
CELLULAR_CL-0.0.4.dist-info/top_level.txt
CELLULAR_CL-0.0.4.dist-info/RECORD
